.gitignore
.gitmodules
LICENSE
MANIFEST.in
README.md
build_package.sh
requirements.txt
setup.cfg
setup.py
bopscrk/__main__.py
bopscrk/bopscrk.cfg
bopscrk/bopscrk.py
bopscrk.egg-info/PKG-INFO
bopscrk.egg-info/SOURCES.txt
bopscrk.egg-info/dependency_links.txt
bopscrk.egg-info/entry_points.txt
bopscrk.egg-info/requires.txt
bopscrk.egg-info/top_level.txt
bopscrk/modules/__init__.py
bopscrk/modules/args.py
bopscrk/modules/auxiliars.py
bopscrk/modules/banners.py
bopscrk/modules/color.py
bopscrk/modules/combinators.py
bopscrk/modules/config.py
bopscrk/modules/excluders.py
bopscrk/modules/main.py
bopscrk/modules/transforms.py
bopscrk/modules/lyricpass/__init__.py
bopscrk/modules/lyricpass/lyricpass.py
img/bopscrk-2.3.gif
img/bopscrk-2.4.5.gif
img/logo.svg
img/logo_raster.svg
img/lyricpass_demo.png
img/original.gif
img/progressbar_example1.gif
img/progressbar_example2.gif