Metadata-Version: 2.1
Name: bopscrk
Version: 2.4.6
Summary: Generate smart and powerful wordlists
Home-page: https://github.com/r3nt0n/bopscrk
Author: r3nt0n
Author-email: r3nt0n@protonmail.com
License: GNU General Public License v3.0
License-File: LICENSE
